setup.py
cjl_test.egg-info/PKG-INFO
cjl_test.egg-info/SOURCES.txt
cjl_test.egg-info/dependency_links.txt
cjl_test.egg-info/requires.txt
cjl_test.egg-info/top_level.txt
cjltest/__init__.py
cjltest/data_skew.py
cjltest/divide_data.py
cjltest/models.py
cjltest/resnet_cifar.py
cjltest/utils_data.py
cjltest/utils_model.py