Metadata-Version: 1.0
Name: cjl-test
Version: 0.9.7
Summary: some models and utils for study
Home-page: UNKNOWN
Author: Chengjie Li
Author-email: 475168571@qq.com
License: HUST
Platform: UNKNOWN
